homgarapi/__init__.py
homgarapi/__main__.py
homgarapi/api.py
homgarapi/devices.py
homgarapi/logutil.py
homgarapi-0.0.3.dist-info/LICENSE.txt
homgarapi-0.0.3.dist-info/METADATA
homgarapi-0.0.3.dist-info/WHEEL
homgarapi-0.0.3.dist-info/top_level.txt
homgarapi-0.0.3.dist-info/RECORD
