Metadata-Version: 2.1
Name: homgarapi
Version: 0.0.3
Summary: HomGar API client
Home-page: https://github.com/Remboooo/homgarapi
Download-URL: https://github.com/Remboooo/homgarapi/archive/refs/tags/0.0.3.tar.gz
Author: Rembrand van Lakwijk
Author-email: rem@lakwijk.com
License: MIT
Keywords: homgar
Classifier: Development Status :: 3 - Alpha
Classifier: Intended Audience :: Developers
Classifier: License :: OSI Approved :: MIT License
Classifier: Programming Language :: Python :: 3
Classifier: Programming Language :: Python :: 3.10
Classifier: Programming Language :: Python :: 3.11
License-File: LICENSE.txt
Requires-Dist: requests >=2.0.0
Requires-Dist: PyYAML >=5.0.0
Requires-Dist: platformdirs >=4.2.2
